pyfa/__init__.py
pyfa/sim.py
pyfa-0.dist-info/METADATA
pyfa-0.dist-info/WHEEL
pyfa-0.dist-info/top_level.txt
pyfa-0.dist-info/RECORD
